colorhex/__init__.py
colorhex/colorex.py
colorhex-2.64.dist-info/METADATA
colorhex-2.64.dist-info/WHEEL
colorhex-2.64.dist-info/top_level.txt
colorhex-2.64.dist-info/RECORD
